regex_rust-0.4.0.dist-info/METADATA
regex_rust-0.4.0.dist-info/WHEEL
regex_rust-0.4.0.dist-info/license_files/LICENSE
regexrs/__init__.py
regexrs/regexrs.pypy39-pp73-win_amd64.pyd
regex_rust-0.4.0.dist-info/RECORD
